intelmq_monitoring_checkmk/__init__.py
intelmq_monitoring_checkmk/base.py
intelmq_monitoring_checkmk/config.py
intelmq_monitoring_checkmk/helpers.py
intelmq_monitoring_checkmk/run.py
intelmq_monitoring_checkmk/storage.py
intelmq_monitoring_checkmk/wrapper.py
intelmq_monitoring_checkmk/writer.py
intelmq_monitoring_checkmk/checks/__init__.py
intelmq_monitoring_checkmk/checks/bot_status.py
intelmq_monitoring_checkmk/checks/duplicated_processes.py
intelmq_monitoring_checkmk/checks/inactive_enabled_feeds.py
intelmq_monitoring_checkmk/checks/script_wrapper.py
intelmq_monitoring_checkmk-0.6.3.dist-info/licenses/LICENSE
intelmq_monitoring_checkmk-0.6.3.dist-info/METADATA
intelmq_monitoring_checkmk-0.6.3.dist-info/WHEEL
intelmq_monitoring_checkmk-0.6.3.dist-info/entry_points.txt
intelmq_monitoring_checkmk-0.6.3.dist-info/top_level.txt
intelmq_monitoring_checkmk-0.6.3.dist-info/RECORD
