Metadata-Version: 2.4
Name: intelmq_monitoring_checkmk
Version: 0.6.3
Summary: Scripts to monitor IntelMQ instances using CheckMK as a report tool
Author: CERT.at Data & Development Team
License: AGPLv3
Project-URL: Repository, https://github.com/certat/intelmq-monitoring-checkmk
Classifier: Programming Language :: Python :: 3
Requires-Python: >=3.7
License-File: LICENSE
Requires-Dist: intelmq
Requires-Dist: importlib_metadata; python_version < "3.8"
Provides-Extra: dev
Requires-Dist: pytest; extra == "dev"
Requires-Dist: tox>=4; extra == "dev"
Requires-Dist: black; extra == "dev"
Requires-Dist: isort; extra == "dev"
Requires-Dist: freezegun; extra == "dev"
Requires-Dist: flake8; extra == "dev"
Dynamic: license-file
